_cdifflib.cpython-310-darwin.so
cdifflib.py
cdifflib-1.2.9.dist-info/LICENSE
cdifflib-1.2.9.dist-info/METADATA
cdifflib-1.2.9.dist-info/WHEEL
cdifflib-1.2.9.dist-info/top_level.txt
cdifflib-1.2.9.dist-info/RECORD
