Metadata-Version: 2.2
Name: cdifflib
Version: 1.2.9
Summary: C implementation of parts of difflib
Home-page: https://github.com/mduggan/cdifflib
Author: Matthew Duggan
Author-email: Matthew Duggan <mgithub@guarana.org>
License: Copyright (c) 2013, Matthew Duggan
Project-URL: Homepage, https://github.com/mduggan/cdifflib
Project-URL: Bug Tracker, https://github.com/mduggan/cdifflib/issues
Keywords: difflib,c,diff
Classifier: Development Status :: 5 - Production/Stable
Classifier: Environment :: Console
Classifier: Intended Audience :: Developers
Classifier: License :: OSI Approved :: BSD License
Classifier: Operating System :: MacOS :: MacOS X
Classifier: Operating System :: Microsoft :: Windows
Classifier: Operating System :: POSIX
Classifier: Programming Language :: Python
Classifier: Topic :: Software Development
Classifier: Topic :: Text Processing :: General
Requires-Python: >=3.4
License-File: LICENSE
Dynamic: author
Dynamic: home-page
